<?xml version='1.0' encoding='utf-8'?>
<!-- FreeCAD DocumentObject -->
<Document SchemaVersion="4" FileVersion="2">
<Object name="Body013" Extensions="True">
  <Extensions Count="1">
    <Extension type="App::OriginGroupExtension" name="OriginGroupExtension">
    </Extension>
  </Extensions>
  <Properties Count="21" TransientCount="2">
    <_Property name="_ElementMapVersion" type="App::PropertyString" status="234881024"/>
    <_Property name="_GroupTouched" type="App::PropertyBool" status="100663424"/>
    <Property name="AutoGroupSolids" type="App::PropertyBool" status="134217728">
      <Bool value="false"/>
    </Property>
    <Property name="BaseFeature" type="App::PropertyLink">
      <Link value=""/>
    </Property>
    <Property name="ClaimAllChildren" type="App::PropertyBool" status="8">
      <Bool value="false"/>
    </Property>
    <Property name="ColoredElements" type="App::PropertyLinkSubHidden" status="218103808">
      <LinkSub value="" count="0">
      </LinkSub>
    </Property>
    <Property name="ExportMode" type="App::PropertyEnumeration" status="8">
      <Integer value="0"/>
    </Property>
    <Property name="ExpressionEngine" type="App::PropertyExpressionEngine" status="67108864">
      <ExpressionEngine count="0"></ExpressionEngine>
    </Property>
    <Property name="FixShape" type="App::PropertyEnumeration">
      <Integer value="0"/>
    </Property>
    <Property name="Group" type="App::PropertyLinkList">
      <LinkList count="10">
        <Link value="Sketch110"/>
        <Link value="Pad044"/>
        <Link value="Sketch111"/>
        <Link value="Sketch120"/>
        <Link value="Pad045"/>
        <Link value="LinearPattern020"/>
        <Link value="Sketch112"/>
        <Link value="Pocket058"/>
        <Link value="Pocket063"/>
        <Link value="LinearPattern021"/>
      </LinkList>
    </Property>
    <Property name="InvalidShape" type="App::PropertyBool" status="67108864">
      <Bool value="false"/>
    </Property>
    <Property name="Label" type="App::PropertyString" status="134217728">
      <String value="205Plate"/>
    </Property>
    <Property name="Label2" type="App::PropertyString" status="128">
      <String value=""/>
    </Property>
    <Property name="Origin" type="App::PropertyLink" status="67108864">
      <Link value="Origin013"/>
    </Property>
    <Property name="Placement" type="App::PropertyPlacement" status="8388608">
      <PropertyPlacement Px="0" Py="0" Pz="0" Q0="0" Q1="0" Q2="0" Q3="1" A="0" Ox="0" Oy="0" Oz="1"/>
    </Property>
    <Property name="Shape" type="Part::PropertyPartShape">
      <Part HasherIndex="0" ElementMap="1.15.70200.4" brep="1">
<![CDATA[

CASCADE Topology V1, (c) Matra-Datavision
Locations 65
1
              1               0               0               0 
              0               1               0               0 
              0               0               1               0 
1
              1               0               0               0 
              0               1               0               0 
              0               0               1               0 
1
              1               0               0               0 
              0               1               0               0 
              0               0               1               0 
1
              1               0               0               0 
              0               1               0               0 
              0               0               1               0 
2  3 1 4 1 0
1
              1               0               0               0 
              0               1               0               0 
              0               0               1               0 
1
2.22044604925031e-16 -2.22044604925031e-16               1               0 
              1 2.22044604925031e-16 -2.22044604925031e-16               0 
-2.22044604925031e-16               1 2.22044604925031e-16               0 
2  6 1 7 1 3 1 4 1 0
1
              1               0               0               0 
              0               1               0               0 
              0               0               1               0 
2  9 -1 2 -1 4 -1 3 -1 7 -1 6 -1 0
2  9 -1 2 -1 4 -1 3 -1 0
2  9 -1 2 -1 0
1
              1               0               0          41.665 
              0               1               0 -9.25148846420143e-15 
              0               0               1 1.15643605802518e-14 
2  6 1 7 1 13 1 3 1 4 1 0
2  9 -1 2 -1 4 -1 3 -1 13 -1 7 -1 6 -1 0
1
              1               0               0               0 
              0               1               0               0 
              0               0               1               0 
1
              1               0               0 8.32667268468867e-15 
              0               1               0              25 
              0               0               1 -5.55111512312578e-15 
2  16 1 17 1 4 1 0
2  9 -1 2 -1 4 -1 17 -1 16 -1 0
2  3 1 4 1 2 1 0
2  6 1 7 1 0
2  6 1 7 1 13 1 0
1
              1               0               0               0 
              0               1               0               0 
              0               0               1               0 
1
2.22044604925031e-16 -2.22044604925031e-16               1               0 
              1 2.22044604925031e-16 -2.22044604925031e-16               0 
-2.22044604925031e-16               1 2.22044604925031e-16               0 
1
              1               0               0           41.66 
              0               1               0 -9.2503782411768e-15 
              0               0               1 1.1562972801471e-14 
2  23 1 24 1 25 1 3 1 4 1 0
2  9 -1 2 -1 4 -1 3 -1 25 -1 24 -1 23 -1 0
2  23 1 24 1 25 1 16 1 17 1 4 1 0
2  9 -1 2 -1 4 -1 17 -1 16 -1 25 -1 24 -1 23 -1 0
2  13 1 3 1 4 1 2 1 0
1
              1               0               0               0 
              0               1               0               0 
              0               0               1               0 
1
              1 -6.56858655152258e-47 -2.77555756156289e-16 -2.77555756156289e-16 
6.16297582203915e-32               1 2.22044604925031e-16 2.22044604925031e-16 
2.77555756156289e-16 -2.22044604925031e-16               1               1 
2  31 1 32 1 0
2  32 -1 31 -1 0
2  9 -1 2 -1 32 -1 31 -1 0
1
              1               0               0 -8.32667268468867e-16 
              0               1               0 6.66133814775094e-16 
              0               0               1               3 
2  31 1 32 1 36 1 0
2  36 -1 32 -1 31 -1 0
2  9 -1 2 -1 36 -1 32 -1 31 -1 0
2  36 1 2 1 0
1
              1               0               0               0 
              0               1               0               0 
              0               0               1               0 
1
              1               0               0            6.25 
              0               1               0 3.85185988877447e-31 
              0               0               1 1.73472347597681e-15 
2  41 1 42 1 0
2  9 -1 42 -1 41 -1 0
2  9 -1 42 -1 41 -1 32 -1 31 -1 0
2  9 -1 42 -1 41 -1 36 -1 32 -1 31 -1 0
2  36 1 41 1 42 1 0
1
              1               0               0            12.5 
              0               1               0 7.70371977754894e-31 
              0               0               1 3.46944695195361e-15 
2  41 1 48 1 0
2  9 -1 48 -1 41 -1 0
2  9 -1 48 -1 41 -1 32 -1 31 -1 0
2  9 -1 48 -1 41 -1 36 -1 32 -1 31 -1 0
2  36 1 41 1 48 1 0
1
              1               0               0           18.75 
              0               1               0 1.15555796663234e-30 
              0               0               1 5.20417042793042e-15 
2  41 1 54 1 0
2  9 -1 54 -1 41 -1 0
2  9 -1 54 -1 41 -1 32 -1 31 -1 0
2  9 -1 54 -1 41 -1 36 -1 32 -1 31 -1 0
2  36 1 41 1 54 1 0
1
              1               0               0              25 
              0               1               0 1.54074395550979e-30 
              0               0               1 6.93889390390723e-15 
2  41 1 60 1 0
2  9 -1 60 -1 41 -1 0
2  9 -1 60 -1 41 -1 32 -1 31 -1 0
2  9 -1 60 -1 41 -1 36 -1 32 -1 31 -1 0
2  36 1 41 1 60 1 0
Curve2ds 8
1 0 0 0 -1 
1 6.2831853071795862 0 0 -1 
1 0 0 1 0 
1 0 -3 1 0 
1 0 0 0 -1 
1 6.2831853071795862 0 0 -1 
1 0 0 1 0 
1 0 -3 1 0 
Curves 95
1 -24.5 1 2.6821728418717202e-46 1 0 -1.0947644252537633e-47 
1 -3.5527136788005005e-15 -15 1.0000000000000022 1 -2.2204460492503131e-16 2.7755575615628914e-16 
1 0.49999999999999978 -65.158482691991097 1.0000000000000144 0 1 -2.2204460492503131e-16 
1 -5.6621374255882984e-15 -24.5 1.0000000000000053 1 -2.2204460492503131e-16 2.7755575615628914e-16 
1 -24.5 1 2.6821728418717202e-46 1 0 -1.0947644252537633e-47 
1 -24.5 1 2.6821728418717202e-46 1 0 -1.0947644252537633e-47 
1 -24.5 1 2.6821728418717202e-46 1 0 -1.0947644252537633e-47 
1 -24.5 1 2.6821728418717202e-46 1 0 -1.0947644252537633e-47 
1 24.5 1 -2.6821728418717202e-46 0 -1 0 
1 24.5 0 -2.6821728418717202e-46 -1 0 1.0947644252537633e-47 
1 -24.5 0 2.6821728418717202e-46 0 1 0 
1 -2.4424906541753444e-15 -10 1.0000000000000018 1 -2.2204460492503131e-16 2.7755575615628914e-16 
1 0.49999999999999978 -65.158482691991097 1.0000000000000144 0 1 -2.2204460492503131e-16 
1 -3.5527136788005005e-15 -15 1.0000000000000022 1 -2.2204460492503131e-16 2.7755575615628914e-16 
1 41.159999999999997 -65.158482691991097 1.0000000000000144 0 1 -2.2204460492503131e-16 
1 -5.6621374255882984e-15 -24.5 1.0000000000000053 1 -2.2204460492503131e-16 2.7755575615628914e-16 
1 -5.440092820663267e-15 -24.5 5.440092820663267e-15 1 -2.2204460492503131e-16 2.7755575615628914e-16 
1 -5.6621374255882984e-15 -24.5 1.0000000000000053 1 -2.2204460492503131e-16 2.7755575615628914e-16 
1 -5.6621374255882984e-15 -24.5 1.0000000000000053 1 -2.2204460492503131e-16 2.7755575615628914e-16 
1 -24.5 0 2.6821728418717202e-46 0 1 0 
1 -3.5527136788005005e-15 -15 1.0000000000000022 1 -2.2204460492503131e-16 2.7755575615628914e-16 
1 0.49999999999999978 -65.158482691991097 1.0000000000000144 0 1 -2.2204460492503131e-16 
1 -2.4424906541753444e-15 -10 1.0000000000000018 1 -2.2204460492503131e-16 2.7755575615628914e-16 
1 0.49999999999999978 -65.158482691991097 1.0000000000000144 0 1 -2.2204460492503131e-16 
1 0.49999999999999978 -65.158482691991097 1.0000000000000144 0 1 -2.2204460492503131e-16 
1 5.2180482157382357e-15 24.5 0.99999999999999456 1 -2.2204460492503131e-16 2.7755575615628914e-16 
1 5.2180482157382357e-15 24.5 0.99999999999999456 1 -2.2204460492503131e-16 2.7755575615628914e-16 
1 5.2180482157382357e-15 24.5 0.99999999999999456 1 -2.2204460492503131e-16 2.7755575615628914e-16 
1 5.2180482157382357e-15 24.5 0.99999999999999456 1 -2.2204460492503131e-16 2.7755575615628914e-16 
1 5.440092820663267e-15 24.5 -5.440092820663267e-15 1 -2.2204460492503131e-16 2.7755575615628914e-16 
1 24.5 1 -2.6821728418717202e-46 0 -1 0 
1 24.5 0 -2.6821728418717202e-46 -1 0 1.0947644252537633e-47 
1 8.1898313570236159 -21.452534655493995 8.6898313570236159 0.60812040241134302 -0.51027360537473687 0.6081204024113428 
1 4.5000000000000009 -65.158482691991097 5.0000000000000133 0 1 -2.2204460492503131e-16 
1 -6.8901268921968786 -16.201052749595689 -6.3901268921968715 -0.60812040241134313 -0.51027360537473687 -0.6081204024113428 
1 -5.1861622828906209e-15 -18.356398524709121 5.0000000000000036 1 -2.2204460492503131e-16 2.7755575615628914e-16 
1 24.287775819303938 -29.15747708716242 17.872224180696044 0.60812040241134369 0.51027360537473665 -0.60812040241134258 
1 -3.5527136788005005e-15 -15 1.0000000000000022 1 -2.2204460492503131e-16 2.7755575615628914e-16 
1 41.659999999999997 -65.158482691991097 1.0000000000000144 0 1 -2.2204460492503131e-16 
1 -10 0.99999999999999944 1.0947644252537633e-46 -1 -8.8817841970012528e-17 1.0947644252537633e-47 
1 41.659999999999997 -65.158482691991097 1.0000000000000144 0 1 -2.2204460492503131e-16 
1 -10 0.99999999999999944 1.0947644252537633e-46 -1 -8.8817841970012528e-17 1.0947644252537633e-47 
1 41.659999999999997 -65.158482691991097 1.0000000000000144 0 1 -2.2204460492503131e-16 
1 -24.5 1 2.6821728418717202e-46 1 0 -1.0947644252537633e-47 
1 -2.4424906541753444e-15 -10 1.0000000000000018 1 -2.2204460492503131e-16 2.7755575615628914e-16 
1 -3.5527136788005005e-15 -15 1.0000000000000022 1 -2.2204460492503131e-16 2.7755575615628914e-16 
1 41.159999999999997 -65.158482691991097 1.0000000000000144 0 1 -2.2204460492503131e-16 
1 12.068678735028268 0.2927259402293485 12.568678735028259 0.60812040241134302 -0.51027360537473687 0.6081204024113428 
1 4.5000000000000009 -65.158482691991097 5.0000000000000133 0 1 -2.2204460492503131e-16 
1 -10.768974270201525 5.5442078461276534 -10.268974270201522 -0.60812040241134313 -0.51027360537473687 -0.6081204024113428 
1 41.159999999999997 -65.158482691991097 1.0000000000000144 0 1 -2.2204460492503131e-16 
1 -2.4424906541753444e-15 -10 1.0000000000000018 1 -2.2204460492503131e-16 2.7755575615628914e-16 
1 -2.4424906541753444e-15 -10 1.0000000000000018 1 -2.2204460492503131e-16 2.7755575615628914e-16 
1 -2.5853988894854749e-15 -6.6436014752908781 5.0000000000000009 1 -2.2204460492503131e-16 2.7755575615628914e-16 
1 37.159999999999989 -65.158482691991097 5.0000000000000133 0 1 -2.2204460492503131e-16 
1 39.367734068524442 -8.4961103179272577 2.7922659314755602 -0.60812040241134346 0.51027360537473698 0.60812040241134224 
1 41.159999999999997 -65.158482691991097 1.0000000000000144 0 1 -2.2204460492503131e-16 
1 -2.4424906541753444e-15 -10 1.0000000000000018 1 -2.2204460492503131e-16 2.7755575615628914e-16 
1 -3.5527136788005005e-15 -15 1.0000000000000022 1 -2.2204460492503131e-16 2.7755575615628914e-16 
1 41.159999999999997 -65.158482691991097 1.0000000000000144 0 1 -2.2204460492503131e-16 
1 -5.1861622828906209e-15 -18.356398524709121 5.0000000000000036 1 -2.2204460492503131e-16 2.7755575615628914e-16 
1 20.408928441299288 -7.4122164914390725 21.75107155870068 0.60812040241134369 0.51027360537473665 -0.60812040241134258 
1 -2.5853988894854749e-15 -6.6436014752908781 5.0000000000000009 1 -2.2204460492503131e-16 2.7755575615628914e-16 
1 37.159999999999989 -65.158482691991097 5.0000000000000133 0 1 -2.2204460492503131e-16 
1 43.246581446529106 13.249150277796089 -1.0865814465290935 -0.60812040241134346 0.51027360537473698 0.60812040241134224 
1 10.385669 -12.5 1.0000000000000056 -2.7755575615628909e-16 2.2204460492503136e-16 1 
2 8.885669 -12.5 0 0 0 1 1 0 -0 -0 1 0 1.5
2 8.885669 -12.5 0 0 0 1 1 0 -0 -0 1 0 1.5
1 10.385669 12.5 1 -2.7755575615628909e-16 2.2204460492503136e-16 1 
2 8.885669 12.5 0 0 0 1 1 0 -0 -0 1 0 1.5
2 8.885669 12.5 0 0 0 1 1 0 -0 -0 1 0 1.5
1 10.385669 12.5 1 -2.7755575615628909e-16 2.2204460492503136e-16 1 
2 8.885669 12.5 0 0 0 1 1 0 -0 -0 1 0 1.5
2 8.885669 12.5 0 0 0 1 1 0 -0 -0 1 0 1.5
1 10.385669 12.5 1 -2.7755575615628909e-16 2.2204460492503136e-16 1 
2 8.885669 12.5 0 0 0 1 1 0 -0 -0 1 0 1.5
2 8.885669 12.5 0 0 0 1 1 0 -0 -0 1 0 1.5
1 10.385669 12.5 1 -2.7755575615628909e-16 2.2204460492503136e-16 1 
2 8.885669 12.5 0 0 0 1 1 0 -0 -0 1 0 1.5
2 8.885669 12.5 0 0 0 1 1 0 -0 -0 1 0 1.5
1 10.385669 -12.5 1.0000000000000056 -2.7755575615628909e-16 2.2204460492503136e-16 1 
2 8.885669 -12.5 0 0 0 1 1 0 -0 -0 1 0 1.5
2 8.885669 -12.5 0 0 0 1 1 0 -0 -0 1 0 1.5
1 10.385669 -12.5 1.0000000000000056 -2.7755575615628909e-16 2.2204460492503136e-16 1 
2 8.885669 -12.5 0 0 0 1 1 0 -0 -0 1 0 1.5
2 8.885669 -12.5 0 0 0 1 1 0 -0 -0 1 0 1.5
1 10.385669 -12.5 1.0000000000000056 -2.7755575615628909e-16 2.2204460492503136e-16 1 
2 8.885669 -12.5 0 0 0 1 1 0 -0 -0 1 0 1.5
2 8.885669 -12.5 0 0 0 1 1 0 -0 -0 1 0 1.5
1 10.385669 -12.5 1.0000000000000056 -2.7755575615628909e-16 2.2204460492503136e-16 1 
2 8.885669 -12.5 0 0 0 1 1 0 -0 -0 1 0 1.5
2 8.885669 -12.5 0 0 0 1 1 0 -0 -0 1 0 1.5
1 10.385669 12.5 1 -2.7755575615628909e-16 2.2204460492503136e-16 1 
2 8.885669 12.5 0 0 0 1 1 0 -0 -0 1 0 1.5
2 8.885669 12.5 0 0 0 1 1 0 -0 -0 1 0 1.5
Polygon3D 0
PolygonOnTriangulations 0
Surfaces 59
1 -5.6621374255882984e-15 -24.5 1.0000000000000053 -2.7755575615628909e-16 2.2204460492503136e-16 1 2.2204460492503131e-16 1 -2.2204460492503131e-16 -1 2.2204460492503126e-16 -2.7755575615628914e-16 
1 -1.1102230246251565e-16 3.552713678800501e-17 0.5 1 -2.2204460492503126e-16 2.2204460492503155e-16 -2.2204460492503155e-16 0 1 -2.2204460492503126e-16 -1 -4.9303806576313282e-32 
1 0.49999999999999978 -65.158482691991097 1.0000000000000144 0 2.2204460492503131e-16 1 -1 0 0 0 -1 2.2204460492503131e-16 
1 -5.6621374255882984e-15 -24.5 1.0000000000000053 -2.7755575615628909e-16 2.2204460492503136e-16 1 2.2204460492503131e-16 1 -2.2204460492503131e-16 -1 2.2204460492503126e-16 -2.7755575615628914e-16 
1 -5.440092820663267e-15 -24.5 5.440092820663267e-15 -2.2204460492503136e-16 -1 2.2204460492503131e-16 -2.2204460492503131e-16 2.2204460492503136e-16 1 -1 2.2204460492503131e-16 -2.2204460492503136e-16 
1 -5.6621374255882984e-15 -24.5 1.0000000000000053 -2.7755575615628909e-16 2.2204460492503136e-16 1 2.2204460492503131e-16 1 -2.2204460492503131e-16 -1 2.2204460492503126e-16 -2.7755575615628914e-16 
1 0.49999999999999978 -65.158482691991097 1.0000000000000144 0 2.2204460492503131e-16 1 -1 0 0 0 -1 2.2204460492503131e-16 
1 -5.6621374255882984e-15 -24.5 1.0000000000000053 -2.7755575615628909e-16 2.2204460492503136e-16 1 2.2204460492503131e-16 1 -2.2204460492503131e-16 -1 2.2204460492503126e-16 -2.7755575615628914e-16 
1 5.2180482157382357e-15 24.5 0.99999999999999456 2.2204460492503136e-16 1 -2.2204460492503131e-16 2.2204460492503131e-16 -2.2204460492503136e-16 -1 -1 2.2204460492503131e-16 -2.2204460492503136e-16 
1 5.440092820663267e-15 24.5 -5.440092820663267e-15 2.7755575615628909e-16 -2.2204460492503136e-16 -1 -2.2204460492503131e-16 -1 2.2204460492503131e-16 -1 2.2204460492503126e-16 -2.7755575615628914e-16 
1 0.49999999999999978 -65.158482691991097 1.0000000000000144 0.70710678118654735 -1.5700924586837754e-16 -0.70710678118654768 0.70710678118654768 1.5700924586837747e-16 0.70710678118654735 0 -1 2.2204460492503131e-16 
1 -3.5527136788005005e-15 -15 1.0000000000000022 8.3133653270719535e-18 -0.76604444311897812 -0.64278760968653936 -3.128235565709223e-16 -0.64278760968653936 0.76604444311897812 -1 1.9471069886944361e-16 -2.4498047541490983e-16 
1 -5.6621374255882984e-15 -24.5 1.0000000000000053 -2.7755575615628909e-16 2.2204460492503136e-16 1 2.2204460492503131e-16 1 -2.2204460492503131e-16 -1 2.2204460492503126e-16 -2.7755575615628914e-16 
1 -5.6621374255882984e-15 -24.5 1.0000000000000053 -2.7755575615628909e-16 2.2204460492503136e-16 1 2.2204460492503131e-16 1 -2.2204460492503131e-16 -1 2.2204460492503126e-16 -2.7755575615628914e-16 
1 -1.1102230246251565e-16 3.552713678800501e-17 0.5 1 -2.2204460492503126e-16 2.2204460492503155e-16 -2.2204460492503155e-16 0 1 -2.2204460492503126e-16 -1 -4.9303806576313282e-32 
1 -5.6621374255882984e-15 -24.5 1.0000000000000053 -2.7755575615628909e-16 2.2204460492503136e-16 1 2.2204460492503131e-16 1 -2.2204460492503131e-16 -1 2.2204460492503126e-16 -2.7755575615628914e-16 
1 0.49999999999999978 -65.158482691991097 1.0000000000000144 0.70710678118654735 -1.5700924586837754e-16 -0.70710678118654768 0.70710678118654768 1.5700924586837747e-16 0.70710678118654735 0 -1 2.2204460492503131e-16 
1 -5.6621374255882984e-15 -24.5 1.0000000000000053 -2.7755575615628909e-16 2.2204460492503136e-16 1 2.2204460492503131e-16 1 -2.2204460492503131e-16 -1 2.2204460492503126e-16 -2.7755575615628914e-16 
1 -5.6621374255882984e-15 -24.5 1.0000000000000053 -2.7755575615628909e-16 2.2204460492503136e-16 1 2.2204460492503131e-16 1 -2.2204460492503131e-16 -1 2.2204460492503126e-16 -2.7755575615628914e-16 
1 -5.1861622828906209e-15 -18.356398524709121 5.0000000000000036 -2.7755575615628909e-16 2.2204460492503136e-16 1 2.2204460492503131e-16 1 -2.2204460492503131e-16 -1 2.2204460492503126e-16 -2.7755575615628914e-16 
1 -2.5853988894854749e-15 -6.643601475290879 5.0000000000000009 3.4850543678181023e-16 0.7660444431189779 -0.64278760968653958 2.7368514883816206e-17 -0.64278760968653958 -0.7660444431189779 -1 2.4937851098061928e-16 -2.4498047541490968e-16 
1 37.159999999999989 -65.158482691991097 5.0000000000000133 -0.70710678118654691 -1.5700924586837766e-16 -0.70710678118654824 0.70710678118654824 -1.5700924586837737e-16 -0.70710678118654691 0 -1 2.2204460492503131e-16 
1 41.659999999999997 -65.158482691991097 1.0000000000000144 0 2.2204460492503131e-16 1 -1 0 0 0 -1 2.2204460492503131e-16 
1 -5.6621374255882984e-15 -24.5 1.0000000000000053 -2.7755575615628909e-16 2.2204460492503136e-16 1 2.2204460492503131e-16 1 -2.2204460492503131e-16 -1 2.2204460492503126e-16 -2.7755575615628914e-16 
1 41.659999999999997 -65.158482691991097 1.0000000000000144 0 2.2204460492503131e-16 1 -1 0 0 0 -1 2.2204460492503131e-16 
1 -3.5527136788005005e-15 -15 1.0000000000000022 8.3133653270719535e-18 -0.76604444311897812 -0.64278760968653936 -3.128235565709223e-16 -0.64278760968653936 0.76604444311897812 -1 1.9471069886944361e-16 -2.4498047541490983e-16 
1 -5.1861622828906209e-15 -18.356398524709121 5.0000000000000036 -2.7755575615628909e-16 2.2204460492503136e-16 1 2.2204460492503131e-16 1 -2.2204460492503131e-16 -1 2.2204460492503126e-16 -2.7755575615628914e-16 
1 -2.5853988894854749e-15 -6.643601475290879 5.0000000000000009 3.4850543678181023e-16 0.7660444431189779 -0.64278760968653958 2.7368514883816206e-17 -0.64278760968653958 -0.7660444431189779 -1 2.4937851098061928e-16 -2.4498047541490968e-16 
1 37.159999999999989 -65.158482691991097 5.0000000000000133 -0.70710678118654691 -1.5700924586837766e-16 -0.70710678118654824 0.70710678118654824 -1.5700924586837737e-16 -0.70710678118654691 0 -1 2.2204460492503131e-16 
2 8.885669 -12.5 1.0000000000000051 2.7755575615628909e-16 -2.2204460492503136e-16 -1 1 6.1629758220391547e-32 2.7755575615628909e-16 -0 1 -2.2204460492503136e-16 1.5
1 8.885669 0 1.0000000000000022 -2.8372366184865109e-16 2.2036223261820951e-16 1 1 0 2.8372366184865109e-16 6.2521979571582664e-32 1 -2.2036223261820951e-16 
1 8.885669 0 1.0000000000000022 -2.8372366184865109e-16 2.2036223261820951e-16 1 1 0 2.8372366184865109e-16 6.2521979571582664e-32 1 -2.2036223261820951e-16 
2 8.885669 12.5 0.99999999999999956 2.7755575615628909e-16 -2.2204460492503136e-16 -1 1 6.1629758220391547e-32 2.7755575615628909e-16 -0 1 -2.2204460492503136e-16 1.5
1 8.885669 0 1.0000000000000022 -2.8372366184865109e-16 2.2036223261820951e-16 1 1 0 2.8372366184865109e-16 6.2521979571582664e-32 1 -2.2036223261820951e-16 
1 8.885669 0 1.0000000000000022 -2.8372366184865109e-16 2.2036223261820951e-16 1 1 0 2.8372366184865109e-16 6.2521979571582664e-32 1 -2.2036223261820951e-16 
2 8.885669 12.5 0.99999999999999956 2.7755575615628909e-16 -2.2204460492503136e-16 -1 1 6.1629758220391547e-32 2.7755575615628909e-16 -0 1 -2.2204460492503136e-16 1.5
1 8.885669 0 1.0000000000000022 -2.8372366184865109e-16 2.2036223261820951e-16 1 1 0 2.8372366184865109e-16 6.2521979571582664e-32 1 -2.2036223261820951e-16 
1 8.885669 0 1.0000000000000022 -2.8372366184865109e-16 2.2036223261820951e-16 1 1 0 2.8372366184865109e-16 6.2521979571582664e-32 1 -2.2036223261820951e-16 
2 8.885669 12.5 0.99999999999999956 2.7755575615628909e-16 -2.2204460492503136e-16 -1 1 6.1629758220391547e-32 2.7755575615628909e-16 -0 1 -2.2204460492503136e-16 1.5
1 8.885669 0 1.0000000000000022 -2.8372366184865109e-16 2.2036223261820951e-16 1 1 0 2.8372366184865109e-16 6.2521979571582664e-32 1 -2.2036223261820951e-16 
1 8.885669 0 1.0000000000000022 -2.8372366184865109e-16 2.2036223261820951e-16 1 1 0 2.8372366184865109e-16 6.2521979571582664e-32 1 -2.2036223261820951e-16 
2 8.885669 12.5 0.99999999999999956 2.7755575615628909e-16 -2.2204460492503136e-16 -1 1 6.1629758220391547e-32 2.7755575615628909e-16 -0 1 -2.2204460492503136e-16 1.5
1 8.885669 0 1.0000000000000022 -2.8372366184865109e-16 2.2036223261820951e-16 1 1 0 2.8372366184865109e-16 6.2521979571582664e-32 1 -2.2036223261820951e-16 
1 8.885669 0 1.0000000000000022 -2.8372366184865109e-16 2.2036223261820951e-16 1 1 0 2.8372366184865109e-16 6.2521979571582664e-32 1 -2.2036223261820951e-16 
2 8.885669 -12.5 1.0000000000000051 2.7755575615628909e-16 -2.2204460492503136e-16 -1 1 6.1629758220391547e-32 2.7755575615628909e-16 -0 1 -2.2204460492503136e-16 1.5
1 8.885669 0 1.0000000000000022 -2.8372366184865109e-16 2.2036223261820951e-16 1 1 0 2.8372366184865109e-16 6.2521979571582664e-32 1 -2.2036223261820951e-16 
1 8.885669 0 1.0000000000000022 -2.8372366184865109e-16 2.2036223261820951e-16 1 1 0 2.8372366184865109e-16 6.2521979571582664e-32 1 -2.2036223261820951e-16 
2 8.885669 -12.5 1.0000000000000051 2.7755575615628909e-16 -2.2204460492503136e-16 -1 1 6.1629758220391547e-32 2.7755575615628909e-16 -0 1 -2.2204460492503136e-16 1.5
1 8.885669 0 1.0000000000000022 -2.8372366184865109e-16 2.2036223261820951e-16 1 1 0 2.8372366184865109e-16 6.2521979571582664e-32 1 -2.2036223261820951e-16 
1 8.885669 0 1.0000000000000022 -2.8372366184865109e-16 2.2036223261820951e-16 1 1 0 2.8372366184865109e-16 6.2521979571582664e-32 1 -2.2036223261820951e-16 
2 8.885669 -12.5 1.0000000000000051 2.7755575615628909e-16 -2.2204460492503136e-16 -1 1 6.1629758220391547e-32 2.7755575615628909e-16 -0 1 -2.2204460492503136e-16 1.5
1 8.885669 0 1.0000000000000022 -2.8372366184865109e-16 2.2036223261820951e-16 1 1 0 2.8372366184865109e-16 6.2521979571582664e-32 1 -2.2036223261820951e-16 
1 8.885669 0 1.0000000000000022 -2.8372366184865109e-16 2.2036223261820951e-16 1 1 0 2.8372366184865109e-16 6.2521979571582664e-32 1 -2.2036223261820951e-16 
2 8.885669 -12.5 1.0000000000000051 2.7755575615628909e-16 -2.2204460492503136e-16 -1 1 6.1629758220391547e-32 2.7755575615628909e-16 -0 1 -2.2204460492503136e-16 1.5
1 8.885669 0 1.0000000000000022 -2.8372366184865109e-16 2.2036223261820951e-16 1 1 0 2.8372366184865109e-16 6.2521979571582664e-32 1 -2.2036223261820951e-16 
1 8.885669 0 1.0000000000000022 -2.8372366184865109e-16 2.2036223261820951e-16 1 1 0 2.8372366184865109e-16 6.2521979571582664e-32 1 -2.2036223261820951e-16 
2 8.885669 12.5 0.99999999999999956 2.7755575615628909e-16 -2.2204460492503136e-16 -1 1 6.1629758220391547e-32 2.7755575615628909e-16 -0 1 -2.2204460492503136e-16 1.5
1 8.885669 0 1.0000000000000022 -2.8372366184865109e-16 2.2036223261820951e-16 1 1 0 2.8372366184865109e-16 6.2521979571582664e-32 1 -2.2036223261820951e-16 
1 8.885669 0 1.0000000000000022 -2.8372366184865109e-16 2.2036223261820951e-16 1 1 0 2.8372366184865109e-16 6.2521979571582664e-32 1 -2.2036223261820951e-16 
Triangulations 0

TShapes 284
Ve
1.00000006354842e-07
-5.6621374255883e-15 -24.5 1.00000000000001
0 0

0101101
*
Ve
1.00000006354842e-07
-3.5527136788005e-15 -15 1
0 0

0101101
*
Ed
 1.00000006354842e-07 1 1 0
1  1 0 0 9.5
0

0101000
+284 10 -283 10 *
Ve
1.50000001803899e-07
0.5 -15 1
0 0

0101101
*
Ed
 1.00000001110223e-07 1 1 0
1  2 0 0 0.500000000000003
0

0101000
+283 11 -281 11 *
Ve
1.00000000222045e-07
0.5 -24.5 1.00000000000001
0 0

0101101
*
Ed
 1.00000000222045e-07 1 1 0
1  3 0 40.6584826919911 50.1584826919911
0

0101000
+279 12 -281 12 *
Ed
 1.00000000222045e-07 1 1 0
1  4 0 0 0.500000000000005
0

0101000
+284 11 -279 11 *
Wi

0101100
-282 8 -280 5 +278 0 +277 5 *
Fa
0  1e-07 1 5

0101000
+276 0 *
Ve
1.00000007257987e-07
-2.44249065417534e-15 -10 1
0 0

0101101
*
Ed
 1.00000004745184e-07 1 1 0
1  5 0 9.5 14.5
0

0101000
+283 10 -274 10 *
Ve
1.00000007809292e-07
4.77395900588817e-15 10 0.999999999999997
0 0

0101101
*
Ed
 1.00000007257987e-07 1 1 0
1  6 0 14.5 34.5
0

0101000
+274 10 -272 10 *
Ve
1.00000009333652e-07
5.88418203051333e-15 15 0.999999999999996
0 0

0101101
*
Ed
 1.00000007809292e-07 1 1 0
1  7 0 34.5 39.5
0

0101000
+272 10 -270 10 *
Ve
1.00000008843078e-07
5.21804821573824e-15 24.5 0.999999999999995
0 0

0101101
*
Ed
 1.00000008843078e-07 1 1 0
1  8 0 39.5 49
0

0101000
+270 10 -268 10 *
Ve
1e-07
5.44009282066327e-15 24.5 -5.44009282066327e-15
0 0

0101101
*
Ed
 1e-07 1 1 0
1  9 0 0 1
0

0101000
+268 10 -266 10 *
Ve
1e-07
-5.44009282066327e-15 -24.5 5.44009282066327e-15
0 0

0101101
*
Ed
 1e-07 1 1 0
1  10 0 0 49
0

0101000
+266 10 -264 10 *
Ed
 1e-07 1 1 0
1  11 0 0 1
0

0101000
+264 10 -284 10 *
Wi

0101100
+282 8 +273 8 +271 8 +269 8 +267 8 +265 8 +263 8 +262 8 *
Fa
0  1e-07 2 5

0101000
-261 0 *
Ve
1.50000007232658e-07
0.5 -10 1
0 0

0101101
*
Ed
 1.00000000444089e-07 1 1 0
1  12 0 0 0.500000000000002
0

0101000
+274 11 -259 11 *
Ed
 1e-07 1 1 0
1  13 0 50.1584826919911 55.1584826919911
0

0101000
+281 12 -259 12 *
Wi

0101100
+280 5 -273 8 -258 5 +257 0 *
Fa
0  1e-07 3 0

0101000
+256 0 *
Ve
1.50000012121276e-07
41.16 -15 1.00000000000001
0 0

0101101
*
Ed
 1.00000001110223e-07 1 1 0
1  14 0 0.500000000000003 41.16
0

0101000
+281 11 -254 11 *
Ve
1.00000011546319e-07
41.16 -24.5 1.00000000000001
0 0

0101101
*
Ed
 1.00000011546319e-07 1 1 0
1  15 0 40.6584826919911 50.1584826919911
0

0101000
+252 12 -254 12 *
Ed
 1e-07 1 1 0
1  16 0 0.500000000000005 41.16
0

0101000
+279 11 -252 11 *
Wi

0101100
-278 0 -253 5 +251 0 +250 5 *
Fa
0  1e-07 4 5

0101000
+249 0 *
Ve
1e-07
41.665 -24.5 1.70044534009151e-14
0 0

0101101
*
Ed
 1e-07 1 1 0
1  17 0 0 41.665
0

0101000
+264 11 -247 11 *
Ve
1.00000011546319e-07
41.66 -24.5 1.00000000000001
0 0

0101101
*
Ed
 1.00000011546319e-07 1 1 0
1  18 0 41.16 41.66
0

0101000
+252 11 -245 11 *
Ve
1e-07
41.665 -24.5 1.00000000000002
0 0

0101101
*
Ed
 1e-07 1 1 0
1  19 0 41.66 41.665
0

0101000
+245 11 -243 11 *
Ed
 1e-07 1 1 0
1  20 0 0 1
0

0101000
+247 15 -243 15 *
Wi

0101100
+246 5 -277 5 -250 5 -244 5 -242 5 -262 8 +241 14 *
Fa
0  1e-07 5 5

0101000
+240 0 *
Ve
1.50000005259224e-07
0.5 10 0.999999999999997
0 0

0101101
*
Ed
 1.00000001110223e-07 1 1 0
1  21 0 0 0.499999999999995
0

0101000
+272 19 -238 19 *
Ed
 1.00000000111022e-07 1 1 0
1  22 0 55.1584826919911 75.1584826919911
0

0101000
+259 12 -238 12 *
Wi

0101100
+258 5 -271 8 -237 18 +236 0 *
Fa
0  1e-07 6 5

0101000
+235 0 *
Ve
1.50000007108896e-07
0.5 15 0.999999999999996
0 0

0101101
*
Ed
 1.00000000444089e-07 1 1 0
1  23 0 0 0.499999999999994
0

0101000
+270 19 -233 19 *
Ed
 1e-07 1 1 0
1  24 0 75.1584826919911 80.1584826919911
0

0101000
+238 12 -233 12 *
Wi

0101100
+237 18 -269 8 -232 18 +231 0 *
Fa
0  1e-07 7 0

0101000
+230 0 *
Ve
1.00000000111022e-07
0.5 24.5 0.999999999999995
0 0

0101101
*
Ed
 1.00000000111022e-07 1 1 0
1  25 0 80.1584826919911 89.6584826919911
0

0101000
+233 12 -228 12 *
Ed
 1.00000000111022e-07 1 1 0
1  26 0 0 0.499999999999995
0

0101000
+268 11 -228 11 *
Wi

0101100
+227 0 +232 18 -267 8 -226 5 *
Fa
0  1e-07 8 5

0101000
+225 0 *
Ve
1.00000011657342e-07
41.16 24.5 1
0 0

0101101
*
Ed
 1e-07 1 1 0
1  27 0 0.499999999999995 41.16
0

0101000
+228 11 -223 11 *
Ve
1.00000011657342e-07
41.66 24.5 1
0 0

0101101
*
Ed
 1.00000011657342e-07 1 1 0
1  28 0 41.16 41.66
0

0101000
+223 11 -221 11 *
Ve
1e-07
41.665 24.5 1.00000000000001
0 0

0101101
*
Ed
 1e-07 1 1 0
1  29 0 41.66 41.665
0

0101000
+221 11 -219 11 *
Ve
1e-07
41.665 24.5 6.12426775958852e-15
0 0

0101101
*
Ed
 1e-07 1 1 0
1  30 0 0 41.665
0

0101000
+266 11 -217 11 *
Ed
 1e-07 1 1 0
1  31 0 0 1
0

0101000
+219 15 -217 15 *
Wi

0101100
+226 5 +222 5 +220 5 +218 5 -216 5 -265 8 +215 14 *
Fa
0  1e-07 9 5

0101000
+214 0 *
Ed
 1e-07 1 1 0
1  32 0 0 49
0

0101000
+217 15 -247 15 *
Wi

0101100
+216 0 -246 0 -263 21 +212 22 *
Fa
0  1e-07 10 0

0101000
+211 0 *
Ve
1.50000003202373e-07
4.5 -18.3563985247091 5
0 0

0101101
*
Ed
 1.5e-07 1 1 0
1  33 0 -12.6452448010815 -6.06760000551297
0

0101000
+281 12 -209 12 *
Ve
1.50000005475099e-07
4.5 -6.64360147529088 5
0 0

0101101
*
Ed
 1.00000001776357e-07 1 1 0
1  34 0 46.802084167282 58.5148812167002
0

0101000
+209 12 -207 12 *
Ed
 1.5e-07 1 1 0
1  35 0 -18.7300522183309 -12.1524074227624
0

0101000
+207 12 -259 12 *
Wi

0101100
-208 0 -206 0 -205 0 +257 0 *
Fa
0  1e-07 11 0

0101000
+204 0 *
Ve
1.50000019214237e-07
37.16 -18.3563985247091 5.00000000000001
0 0

0101101
*
Ed
 1e-07 1 1 0
1  36 0 4.50000000000001 37.16
0

0101000
+209 11 -202 11 *
Ed
 1.5e-07 1 1 0
1  37 0 21.1672295973866 27.7448743929551
0

0101000
+202 12 -254 12 *
Wi

0101100
-208 0 -201 5 -200 0 +253 5 *
Fa
0  1e-07 12 5

0101000
+199 0 *
Ve
1.00000011656813e-07
41.66 -15 1.00000000000001
0 0

0101101
*
Ed
 1.00000010436096e-07 1 1 0
1  38 0 41.16 41.66
0

0101000
+254 11 -197 11 *
Ed
 1.00000011546319e-07 1 1 0
1  39 0 40.6584826919911 50.1584826919911
0

0101000
+245 12 -197 12 *
Wi

0101100
-251 0 -196 5 +195 0 +244 5 *
Fa
0  1e-07 13 5

0101000
+194 0 *
Ve
1.00000011656813e-07
41.66 -10 1.00000000000001
0 0

0101101
*
Ed
 1.00000011656813e-07 1 1 0
1  40 0 0 5
0

0101000
+192 27 -197 27 *
Ve
1.00000014131268e-07
41.66 9.99999999999999 1.00000000000001
0 0

0101101
*
Ed
 1.00000011546319e-07 1 1 0
1  41 0 55.1584826919911 75.1584826919911
0

0101000
+192 12 -190 12 *
Ve
1.00000014131268e-07
41.66 15 1.00000000000001
0 0

0101101
*
Ed
 1.00000014131268e-07 1 1 0
1  42 0 0 5
0

0101000
+188 29 -190 29 *
Ed
 1.00000011546319e-07 1 1 0
1  43 0 80.1584826919911 89.6584826919911
0

0101000
+188 12 -221 12 *
Ed
 1e-07 1 1 0
1  44 0 0 49
0

0101000
+243 15 -219 15 *
Wi

0101100
-195 0 +191 26 -189 0 +187 28 -186 0 -218 5 +185 14 +242 5 *
Fa
0  1e-07 14 5

0101000
+184 0 *
Wi

0101100
+185 0 +215 0 +212 0 +241 0 *
Fa
0  1e-07 15 0

0101000
-182 21 *
Ve
1.50000009339081e-07
41.16 -10 1.00000000000001
0 0

0101101
*
Ed
 1.00000000444089e-07 1 1 0
1  45 0 0.500000000000002 41.16
0

0101000
+259 11 -180 11 *
Ve
1.50000016197085e-07
41.16 9.99999999999999 1
0 0

0101101
*
Ed
 1.00000001110223e-07 1 1 0
1  46 0 0.499999999999995 41.16
0

0101000
+238 19 -178 19 *
Ed
 1.00000011435297e-07 1 1 0
1  47 0 55.1584826919911 75.1584826919911
0

0101000
+180 12 -178 12 *
Wi

0101100
+179 5 -236 0 -177 18 +176 0 *
Fa
0  1e-07 16 5

0101000
+175 0 *
Ve
1.50000007536444e-07
4.5 6.64360147529088 5
0 0

0101101
*
Ed
 1.5e-07 1 1 0
1  48 0 -19.0236648682657 -12.4460200726972
0

0101000
+238 12 -173 12 *
Ve
1.50000008042798e-07
4.5 18.3563985247091 5
0 0

0101101
*
Ed
 1.00000002664535e-07 1 1 0
1  49 0 71.802084167282 83.5148812167002
0

0101000
+173 12 -171 12 *
Ed
 1.5e-07 1 1 0
1  50 0 -25.1084722855151 -18.5308274899466
0

0101000
+171 12 -233 12 *
Wi

0101100
-172 0 -170 0 -169 0 +231 0 *
Fa
0  1e-07 17 0

0101000
+168 0 *
Ve
1.50000024197769e-07
41.16 15 1
0 0

0101101
*
Ed
 1.00000011435297e-07 1 1 0
1  51 0 80.1584826919911 89.6584826919911
0

0101000
+166 12 -223 12 *
Ed
 1.00000000444089e-07 1 1 0
1  52 0 0.499999999999994 41.16
0

0101000
+233 19 -166 19 *
Wi

0101100
+165 0 +164 18 -227 0 -222 5 *
Fa
0  1e-07 18 5

0101000
+163 0 *
Ed
 1.0000001110223e-07 1 1 0
1  53 0 41.16 41.66
0

0101000
+166 19 -188 19 *
Wi

0101100
+186 0 +161 18 -165 0 -220 5 *
Fa
0  1e-07 19 5

0101000
+160 0 *
Ve
1.50000010204393e-07
37.16 -6.64360147529089 5.00000000000001
0 0

0101101
*
Ed
 1.00000000444089e-07 1 1 0
1  54 0 4.5 37.16
0

0101000
+207 11 -158 11 *
Ed
 1.00000011546319e-07 1 1 0
1  55 0 46.802084167282 58.5148812167002
0

0101000
+202 12 -158 12 *
Wi

0101100
-206 0 -157 5 +156 0 +201 5 *
Fa
0  1e-07 20 5

0101000
+155 0 *
Ed
 1.5e-07 1 1 0
1  56 0 -2.94722216911124 3.63042262645728
0

0101000
+180 12 -158 12 *
Wi

0101100
-205 0 -179 5 -153 0 +157 5 *
Fa
0  1e-07 21 5

0101000
+152 0 *
Ed
 1e-07 1 1 0
1  57 0 50.1584826919911 55.1584826919911
0

0101000
+254 12 -180 12 *
Wi

0101100
-200 0 -150 0 -153 0 +156 0 *
Fa
0  1e-07 22 0

0101000
+149 0 *
Ed
 1.0000001110223e-07 1 1 0
1  58 0 41.16 41.66
0

0101000
+180 11 -192 11 *
Wi

0101100
-191 26 +196 5 -150 0 -147 5 *
Fa
0  1e-07 23 0

0101000
+146 0 *
Ed
 1.00000010436096e-07 1 1 0
1  59 0 41.16 41.66
0

0101000
+178 19 -190 19 *
Wi

0101100
+147 5 -176 0 -144 18 +189 0 *
Fa
0  1e-07 24 5

0101000
+143 0 *
Ed
 1e-07 1 1 0
1  60 0 75.1584826919911 80.1584826919911
0

0101000
+178 12 -166 12 *
Wi

0101100
+144 18 -141 0 -161 18 -187 28 *
Fa
0  1e-07 25 0

0101000
+140 0 *
Ve
1.50000027647897e-07
37.16 6.64360147529087 5
0 0

0101101
*
Ed
 1e-07 1 1 0
1  61 0 4.5 37.16
0

0101000
+173 19 -138 19 *
Ed
 1.5e-07 1 1 0
1  62 0 27.5456496645708 34.1232944601393
0

0101000
+138 12 -178 12 *
Wi

0101100
-172 0 -137 18 -136 0 +177 18 *
Fa
0  1e-07 26 18

0101000
+135 0 *
Ve
1.50000028876045e-07
37.16 18.3563985247091 5
0 0

0101101
*
Ed
 1.00000000444089e-07 1 1 0
1  63 0 4.5 37.16
0

0101000
+171 19 -133 19 *
Ed
 1.00000011546319e-07 1 1 0
1  64 0 71.802084167282 83.5148812167002
0

0101000
+138 12 -133 12 *
Wi

0101100
-170 0 -132 18 +131 0 +137 18 *
Fa
0  1e-07 27 18

0101000
+130 0 *
Ed
 1.5e-07 1 1 0
1  65 0 3.43119789807298 10.0088426936415
0

0101000
+166 12 -133 12 *
Wi

0101100
-169 0 -164 18 -128 0 +132 18 *
Fa
0  1e-07 28 18

0101000
+127 0 *
Wi

0101100
-136 0 -141 0 -128 0 +131 0 *
Fa
0  1e-07 29 0

0101000
+125 0 *
Sh

0101100
+275 2 -260 2 +255 2 +248 2 +239 2 +234 2 +229 2 +224 2 +213 2 +210 20 
-203 2 +198 2 +193 2 +183 2 +181 30 +174 2 -167 2 +162 2 +159 2 +154 2 
+151 2 -148 2 +145 2 +142 2 +139 2 +134 2 +129 2 +126 2 -124 2 *
Ve
1e-07
10.385669 -12.5 1.00000000000001
0 0

0101101
*
Ve
1e-07
10.385669 -12.5 4.00000000000001
0 0

0101101
*
Ed
 1e-07 1 1 0
1  66 0 0 3
3  1 2CN 30 0 0 3
0

0101000
+122 12 -121 12 *
Ed
 1e-07 1 1 0
1  67 0 0 6.28318530717959
2  3 30 34 0 6.28318530717959
0

0101100
+122 35 -122 35 *
Ed
 1e-07 1 1 0
1  68 0 0 6.28318530717959
2  4 30 38 0 6.28318530717959
0

0101100
+121 39 -121 39 *
Wi

0101100
+120 0 -120 0 -119 33 +118 37 *
Fa
0  1e-07 30 0

0101000
+117 0 *
Wi

0101100
+119 0 *
Fa
0  1e-07 31 0

0101000
+115 33 *
Wi

0101100
+118 0 *
Fa
0  1e-07 32 0

0101000
+113 33 *
Sh

0101100
+116 2 +114 2 -112 40 *
Ve
1e-07
10.385669 12.5 1
0 0

0101101
*
Ve
1e-07
10.385669 12.5 4
0 0

0101101
*
Ed
 1e-07 1 1 0
1  69 0 0 3
3  5 6CN 33 0 0 3
0

0101000
+110 12 -109 12 *
Ed
 1e-07 1 1 0
1  70 0 0 6.28318530717959
2  7 33 34 0 6.28318530717959
0

0101100
+110 35 -110 35 *
Ed
 1e-07 1 1 0
1  71 0 0 6.28318530717959
2  8 33 38 0 6.28318530717959
0

0101100
+109 39 -109 39 *
Wi

0101100
+108 0 -108 0 -107 33 +106 37 *
Fa
0  1e-07 33 0

0101000
+105 0 *
Wi

0101100
+107 0 *
Fa
0  1e-07 34 0

0101000
+103 33 *
Wi

0101100
+106 0 *
Fa
0  1e-07 35 0

0101000
+101 33 *
Sh

0101100
+104 2 +102 2 -100 40 *
Ve
1e-07
16.635669 12.5 1
0 0

0101101
*
Ve
1e-07
16.635669 12.5 4
0 0

0101101
*
Ed
 1e-07 1 1 0
1  72 0 0 3
3  5 6CN 36 0 0 3
0

0101000
+98 44 -97 44 *
Ed
 1e-07 1 1 0
1  73 0 0 6.28318530717959
2  7 36 34 0 6.28318530717959
0

0101100
+98 45 -98 45 *
Ed
 1e-07 1 1 0
1  74 0 0 6.28318530717959
2  8 36 38 0 6.28318530717959
0

0101100
+97 46 -97 46 *
Wi

0101100
+96 0 -96 0 -95 33 +94 37 *
Fa
0  1e-07 36 0

0101000
+93 0 *
Wi

0101100
+95 0 *
Fa
0  1e-07 37 0

0101000
+91 33 *
Wi

0101100
+94 0 *
Fa
0  1e-07 38 0

0101000
+89 33 *
Sh

0101100
+92 43 +90 43 -88 47 *
Ve
1e-07
22.885669 12.5 1
0 0

0101101
*
Ve
1e-07
22.885669 12.5 4
0 0

0101101
*
Ed
 1e-07 1 1 0
1  75 0 0 3
3  5 6CN 39 0 0 3
0

0101000
+86 50 -85 50 *
Ed
 1e-07 1 1 0
1  76 0 0 6.28318530717959
2  7 39 34 0 6.28318530717959
0

0101100
+86 51 -86 51 *
Ed
 1e-07 1 1 0
1  77 0 0 6.28318530717959
2  8 39 38 0 6.28318530717959
0

0101100
+85 52 -85 52 *
Wi

0101100
+84 0 -84 0 -83 33 +82 37 *
Fa
0  1e-07 39 0

0101000
+81 0 *
Wi

0101100
+83 0 *
Fa
0  1e-07 40 0

0101000
+79 33 *
Wi

0101100
+82 0 *
Fa
0  1e-07 41 0

0101000
+77 33 *
Sh

0101100
+80 49 +78 49 -76 53 *
Ve
1e-07
29.135669 12.5 1.00000000000001
0 0

0101101
*
Ve
1e-07
29.135669 12.5 4.00000000000001
0 0

0101101
*
Ed
 1e-07 1 1 0
1  78 0 0 3
3  5 6CN 42 0 0 3
0

0101000
+74 56 -73 56 *
Ed
 1e-07 1 1 0
1  79 0 0 6.28318530717959
2  7 42 34 0 6.28318530717959
0

0101100
+74 57 -74 57 *
Ed
 1e-07 1 1 0
1  80 0 0 6.28318530717959
2  8 42 38 0 6.28318530717959
0

0101100
+73 58 -73 58 *
Wi

0101100
+72 0 -72 0 -71 33 +70 37 *
Fa
0  1e-07 42 0

0101000
+69 0 *
Wi

0101100
+71 0 *
Fa
0  1e-07 43 0

0101000
+67 33 *
Wi

0101100
+70 0 *
Fa
0  1e-07 44 0

0101000
+65 33 *
Sh

0101100
+68 55 +66 55 -64 59 *
Ve
1e-07
16.635669 -12.5 1.00000000000001
0 0

0101101
*
Ve
1e-07
16.635669 -12.5 4.00000000000001
0 0

0101101
*
Ed
 1e-07 1 1 0
1  81 0 0 3
3  1 2CN 45 0 0 3
0

0101000
+62 44 -61 44 *
Ed
 1e-07 1 1 0
1  82 0 0 6.28318530717959
2  3 45 34 0 6.28318530717959
0

0101100
+62 45 -62 45 *
Ed
 1e-07 1 1 0
1  83 0 0 6.28318530717959
2  4 45 38 0 6.28318530717959
0

0101100
+61 46 -61 46 *
Wi

0101100
+60 0 -60 0 -59 33 +58 37 *
Fa
0  1e-07 45 0

0101000
+57 0 *
Wi

0101100
+59 0 *
Fa
0  1e-07 46 0

0101000
+55 33 *
Wi

0101100
+58 0 *
Fa
0  1e-07 47 0

0101000
+53 33 *
Sh

0101100
+56 43 +54 43 -52 47 *
Ve
1e-07
22.885669 -12.5 1.00000000000001
0 0

0101101
*
Ve
1e-07
22.885669 -12.5 4.00000000000001
0 0

0101101
*
Ed
 1e-07 1 1 0
1  84 0 0 3
3  1 2CN 48 0 0 3
0

0101000
+50 50 -49 50 *
Ed
 1e-07 1 1 0
1  85 0 0 6.28318530717959
2  3 48 34 0 6.28318530717959
0

0101100
+50 51 -50 51 *
Ed
 1e-07 1 1 0
1  86 0 0 6.28318530717959
2  4 48 38 0 6.28318530717959
0

0101100
+49 52 -49 52 *
Wi

0101100
+48 0 -48 0 -47 33 +46 37 *
Fa
0  1e-07 48 0

0101000
+45 0 *
Wi

0101100
+47 0 *
Fa
0  1e-07 49 0

0101000
+43 33 *
Wi

0101100
+46 0 *
Fa
0  1e-07 50 0

0101000
+41 33 *
Sh

0101100
+44 49 +42 49 -40 53 *
Ve
1e-07
29.135669 -12.5 1.00000000000001
0 0

0101101
*
Ve
1e-07
29.135669 -12.5 4.00000000000001
0 0

0101101
*
Ed
 1e-07 1 1 0
1  87 0 0 3
3  1 2CN 51 0 0 3
0

0101000
+38 56 -37 56 *
Ed
 1e-07 1 1 0
1  88 0 0 6.28318530717959
2  3 51 34 0 6.28318530717959
0

0101100
+38 57 -38 57 *
Ed
 1e-07 1 1 0
1  89 0 0 6.28318530717959
2  4 51 38 0 6.28318530717959
0

0101100
+37 58 -37 58 *
Wi

0101100
+36 0 -36 0 -35 33 +34 37 *
Fa
0  1e-07 51 0

0101000
+33 0 *
Wi

0101100
+35 0 *
Fa
0  1e-07 52 0

0101000
+31 33 *
Wi

0101100
+34 0 *
Fa
0  1e-07 53 0

0101000
+29 33 *
Sh

0101100
+32 55 +30 55 -28 59 *
Ve
1e-07
35.385669 -12.5 1.00000000000001
0 0

0101101
*
Ve
1e-07
35.385669 -12.5 4.00000000000001
0 0

0101101
*
Ed
 1e-07 1 1 0
1  90 0 0 3
3  1 2CN 54 0 0 3
0

0101000
+26 62 -25 62 *
Ed
 1e-07 1 1 0
1  91 0 0 6.28318530717959
2  3 54 34 0 6.28318530717959
0

0101100
+26 63 -26 63 *
Ed
 1e-07 1 1 0
1  92 0 0 6.28318530717959
2  4 54 38 0 6.28318530717959
0

0101100
+25 64 -25 64 *
Wi

0101100
+24 0 -24 0 -23 33 +22 37 *
Fa
0  1e-07 54 0

0101000
+21 0 *
Wi

0101100
+23 0 *
Fa
0  1e-07 55 0

0101000
+19 33 *
Wi

0101100
+22 0 *
Fa
0  1e-07 56 0

0101000
+17 33 *
Sh

0101100
+20 61 +18 61 -16 65 *
Ve
1e-07
35.385669 12.5 1.00000000000001
0 0

0101101
*
Ve
1e-07
35.385669 12.5 4.00000000000001
0 0

0101101
*
Ed
 1e-07 1 1 0
1  93 0 0 3
3  5 6CN 57 0 0 3
0

0101000
+14 62 -13 62 *
Ed
 1e-07 1 1 0
1  94 0 0 6.28318530717959
2  7 57 34 0 6.28318530717959
0

0101100
+14 63 -14 63 *
Ed
 1e-07 1 1 0
1  95 0 0 6.28318530717959
2  8 57 38 0 6.28318530717959
0

0101100
+13 64 -13 64 *
Wi

0101100
+12 0 -12 0 -11 33 +10 37 *
Fa
0  1e-07 57 0

0101000
+9 0 *
Wi

0101100
+11 0 *
Fa
0  1e-07 58 0

0101000
+7 33 *
Wi

0101100
+10 0 *
Fa
0  1e-07 59 0

0101000
+5 33 *
Sh

0101100
+8 61 +6 61 -4 65 *
So

0100000
+123 0 +111 0 +99 0 +87 0 +75 0 +63 0 +51 0 +39 0 +27 0 +15 0 
+3 0 *
Co

1100000
+2 0 *

+1 1 ]]>
      </Part>
      <ElementMap new="1" count="1"><Element key="Dummy" value="Dummy"/></ElementMap>
      <ElementMap2 count="212">
<![CDATA[
424 PostfixCount 9
Edge
Face
Vertex
;:H-14d2,E
;:H-14d2,V
;:H-14d2,F
;:H14b3,V
;:H14b3,E
;:H14b3,F

MapCount 2

ElementMap 1 425 3

Edge

ChildCount 0

NameCount 96
0
$#10fec.8 0
$#10fee.8 0
$#10ff0.8 0
$#10ff1.8 0
$#10ff2.8 0
$#10ff3.8 0
$#10ff4.8 0
$#10ff5.8 0
$#10ff6.8 0
$#10ff8.8 0
$#10ff9.8 0
$#10ffa.8 0
$#10ffc.8 0
$#10ffe.8 0
$#10fff.8 0
$#11000.8 0
$#11001.8 0
$#11003.8 0
$#11005.8 0
$#11006.8 0
$#11007.8 0
$#11009.8 0
$#1100a.8 0
$#1100c.8 0
$#1100e.8 0
$#1100f.8 0
$#11010.8 0
$#11011.8 0
$#11012.8 0
$#11013.8 0
$#11014.8 0
$#11015.8 0
$#11016.8 0
$#11017.8 0
$#11018.8 0
$#11019.8 0
$#1101a.8 0
$#1101b.8 0
$#1101c.8 0
$#1101d.8 0
$#1101e.8 0
$#1101f.8 0
$#11020.8 0
$#11021.8 0
$#11022.8 0
$#11023.8 0
$#11024.8 0
$#11025.8 0
$#11026.8 0
$#11027.8 0
$#11028.8 0
$#11029.8 0
$#1102a.8 0
$#1102b.8 0
$#1102c.8 0
$#1102d.8 0
$#1102e.8 0
$#1102f.8 0
$#11030.8 0
$#11031.8 0
$#11032.8 0
$#11033.8 0
$#11034.8 0
$#11035.8 0
$#11036.8 0
$#10fc2.4 0
$#10fb6.4 0
$#11064.4 0
$#10fc3.4 0
$#10fb7.4 0
$#11068.4 0
$#11075.4 0
$#11076.4 0
$#11077.4 0
$#11092.4 0
$#11093.4 0
$#11094.4 0
$#110a9.4 0
$#110aa.4 0
$#110ab.4 0
$#11070.4 0
$#11072.4 0
$#11074.4 0
$#11085.4 0
$#11087.4 0
$#11089.4 0
$#1109c.4 0
$#1109e.4 0
$#110a0.4 0
$#110b3.4 0
$#110b5.4 0
$#110b7.4 0
$#110c0.4 0
$#110c1.4 0
$#110c2.4 0

Face

ChildCount 0

NameCount 60
0
$#11037.9 0
$#11039.9 0
$#1103b.9 0
$#1103d.9 0
$#1103e.9 0
$#1103f.9 0
$#11041.9 0
$#11042.9 0
$#11043.9 0
$#1105c.9.1089d 0
$#11045.9 0
$#11046.9 0
$#11047.9 0
$#11049.9 0
$#1104b.9 0
$#1104d.9 0
$#1104e.9 0
$#11050.9 0
$#11051.9 0
$#11052.9 0
$#11053.9 0
$#11054.9 0
$#11055.9 0
$#11056.9 0
$#11057.9 0
$#11058.9 0
$#11059.9 0
$#1105a.9 0
$#1105b.9 0
$#10fbf.6 0
$#10fbc.6 0
$#11066.6 0
$#10fc0.6 0
$#10fbd.6 0
$#11069.6 0
$#1107e.6 0
$#1107f.6 0
$#11080.6 0
$#11095.6 0
$#11096.6 0
$#11097.6 0
$#110ac.6 0
$#110ad.6 0
$#110ae.6 0
$#11079.6 0
$#1107b.6 0
$#1107d.6 0
$#1108b.6 0
$#1108d.6 0
$#1108f.6 0
$#110a2.6 0
$#110a4.6 0
$#110a6.6 0
$#110b9.6 0
$#110bb.6 0
$#110bd.6 0
$#110c3.6 0
$#110c4.6 0
$#110c5.6 0

Vertex

ChildCount 0

NameCount 59
0
$#10fc5.7 0
$#10fc6.7 0
$#10fc7.7 0
$#10fc8.7 0
$#10fc9.7 0
$#10fca.7 0
$#10fcb.7 0
$#10fcc.7 0
$#10fce.7 0
$#10fcf.7 0
$#10fd0.7 0
$#10fd1.7 0
$#10fd2.7 0
$#10fd3.7 0
$#10fd4.7 0
$#10fd5.7 0
$#10fd6.7 0
$#10fd7.7 0
$#10fd8.7 0
$#10fd9.7 0
$#10fda.7 0
$#10fdb.7 0
$#10fdc.7 0
$#10fdd.7 0
$#10fde.7 0
$#10fdf.7 0
$#10fe0.7 0
$#10fe1.7 0
$#10fe2.7 0
$#10fe3.7 0
$#10fe4.7 0
$#10fe5.7 0
$#10fe6.7 0
$#10fe7.7 0
$#10fe8.7 0
$#10fe9.7 0
$#10fea.7 0
$#10feb.7 0
$#10fb9.5 0
$#11062.5 0
$#10fba.5 0
$#11067.5 0
$#1106d.5 0
$#1106e.5 0
$#11090.5 0
$#11091.5 0
$#110a7.5 0
$#110a8.5 0
$#1106b.5 0
$#1106c.5 0
$#11082.5 0
$#11083.5 0
$#11099.5 0
$#1109a.5 0
$#110b0.5 0
$#110b1.5 0
$#110be.5 0
$#110bf.5 0

EndMap

ElementMap 2 424 3

Edge

ChildCount 1
1 0 95 5331 1 ;:H14d2,E;:H14d3:9,E 0

NameCount 0

Face

ChildCount 1
1 0 59 5331 1 ;:H14d2,F;:H14d3:9,F 0

NameCount 0

Vertex

ChildCount 1
1 0 58 5331 1 ;:H14d2,V;:H14d3:9,V 0

NameCount 0

EndMap
]]>
      </ElementMap2>
    </Property>
    <Property name="SingleSolid" type="App::PropertyBool">
      <Bool value="false"/>
    </Property>
    <Property name="Tip" type="App::PropertyLink">
      <Link value="LinearPattern021"/>
    </Property>
    <Property name="TreeRank" type="App::PropertyInteger" status="2184">
      <Integer value="225"/>
    </Property>
    <Property name="ValidateShape" type="App::PropertyBool">
      <Bool value="true"/>
    </Property>
    <Property name="Visibility" type="App::PropertyBool" status="648">
      <Bool value="false"/>
    </Property>
    <Property name="_ExportChildren" type="App::PropertyLinkList" status="218104320">
      <LinkList count="6">
        <Link value="Pad044"/>
        <Link value="Pad045"/>
        <Link value="LinearPattern020"/>
        <Link value="Pocket058"/>
        <Link value="Pocket063"/>
        <Link value="LinearPattern021"/>
      </LinkList>
    </Property>
    <Property name="_GroupVersion" type="App::PropertyInteger" status="218103808">
      <Integer value="1"/>
    </Property>
  </Properties>
</Object>
</Document>
