<?xml version='1.0' encoding='utf-8'?>
<!-- FreeCAD DocumentObject -->
<Document SchemaVersion="4" FileVersion="2">
<Object name="Sketch191" Extensions="True">
  <Extensions Count="1">
    <Extension type="Part::AttachExtension" name="AttachExtension">
    </Extension>
  </Extensions>
  <Properties Count="30" TransientCount="1">
    <_Property name="_ElementMapVersion" type="App::PropertyString" status="234881024"/>
    <Property name="ArcFitTolerance" type="App::PropertyPrecision">
      <Float value="1e-06"/>
    </Property>
    <Property name="AttacherType" type="App::PropertyString" status="8">
      <String value="Attacher::AttachEnginePlane"/>
    </Property>
    <Property name="AttachmentOffset" type="App::PropertyPlacement">
      <PropertyPlacement Px="0" Py="0" Pz="0" Q0="0" Q1="0" Q2="0" Q3="1" A="0" Ox="0" Oy="0" Oz="1"/>
    </Property>
    <Property name="AttachmentSupport" type="App::PropertyLinkSubList">
      <LinkSubList count="1">
        <Link obj="Pad079" sub="Face1" shadow=";#1a594;:H1641,F.Face1"/>
      </LinkSubList>
    </Property>
    <Property name="ColoredElements" type="App::PropertyLinkSubHidden" status="218103808">
      <LinkSub value="" count="0">
      </LinkSub>
    </Property>
    <Property name="Constraints" type="Sketcher::PropertyConstraintList">
      <ConstraintList count="24">
        <Constrain Name="" Type="13" Value="0" First="0" FirstPos="1" Second="-4" SecondPos="0" Third="-2000" ThirdPos="0" LabelDistance="10" LabelPosition="0" IsDriving="1" IsInVirtualSpace="0" IsActive="1" />
        <Constrain Name="" Type="1" Value="0" First="1" FirstPos="2" Second="0" SecondPos="1" Third="-2000" ThirdPos="0" LabelDistance="10" LabelPosition="0" IsDriving="1" IsInVirtualSpace="0" IsActive="1" />
        <Constrain Name="" Type="9" Value="0.7853981633974483" First="0" FirstPos="1" Second="1" SecondPos="2" Third="-2000" ThirdPos="0" LabelDistance="0.9863883256912231" LabelPosition="0" IsDriving="1" IsInVirtualSpace="0" IsActive="1" />
        <Constrain Name="" Type="13" Value="0" First="1" FirstPos="1" Second="-4" SecondPos="0" Third="-2000" ThirdPos="0" LabelDistance="10" LabelPosition="0" IsDriving="1" IsInVirtualSpace="0" IsActive="1" />
        <Constrain Name="" Type="13" Value="0" First="0" FirstPos="2" Second="-3" SecondPos="0" Third="-2000" ThirdPos="0" LabelDistance="10" LabelPosition="0" IsDriving="1" IsInVirtualSpace="0" IsActive="1" />
        <Constrain Name="" Type="1" Value="0" First="2" FirstPos="1" Second="0" SecondPos="2" Third="-2000" ThirdPos="0" LabelDistance="10" LabelPosition="0" IsDriving="1" IsInVirtualSpace="0" IsActive="1" />
        <Constrain Name="" Type="1" Value="0" First="2" FirstPos="2" Second="-3" SecondPos="2" Third="-2000" ThirdPos="0" LabelDistance="10" LabelPosition="0" IsDriving="1" IsInVirtualSpace="0" IsActive="1" />
        <Constrain Name="" Type="1" Value="0" First="3" FirstPos="1" Second="2" SecondPos="2" Third="-2000" ThirdPos="0" LabelDistance="10" LabelPosition="0" IsDriving="1" IsInVirtualSpace="0" IsActive="1" />
        <Constrain Name="" Type="1" Value="0" First="3" FirstPos="2" Second="-4" SecondPos="2" Third="-2000" ThirdPos="0" LabelDistance="10" LabelPosition="0" IsDriving="1" IsInVirtualSpace="0" IsActive="1" />
        <Constrain Name="" Type="1" Value="0" First="4" FirstPos="1" Second="3" SecondPos="2" Third="-2000" ThirdPos="0" LabelDistance="10" LabelPosition="0" IsDriving="1" IsInVirtualSpace="0" IsActive="1" />
        <Constrain Name="" Type="1" Value="0" First="4" FirstPos="2" Second="1" SecondPos="1" Third="-2000" ThirdPos="0" LabelDistance="10" LabelPosition="0" IsDriving="1" IsInVirtualSpace="0" IsActive="1" />
        <Constrain Name="" Type="2" Value="0" First="0" FirstPos="2" Second="1" SecondPos="1" Third="-2000" ThirdPos="0" LabelDistance="10" LabelPosition="0" IsDriving="1" IsInVirtualSpace="0" IsActive="1" />
        <Constrain Name="" Type="8" Value="0.5" First="4" FirstPos="1" Second="4" SecondPos="2" Third="-2000" ThirdPos="0" LabelDistance="-5.561496734619141" LabelPosition="-3.12058162689209" IsDriving="1" IsInVirtualSpace="0" IsActive="1" />
        <Constrain Name="" Type="1" Value="0" First="5" FirstPos="2" Second="6" SecondPos="1" Third="-2000" ThirdPos="0" LabelDistance="10" LabelPosition="0" IsDriving="1" IsInVirtualSpace="0" IsActive="1" />
        <Constrain Name="" Type="1" Value="0" First="6" FirstPos="2" Second="7" SecondPos="1" Third="-2000" ThirdPos="0" LabelDistance="10" LabelPosition="0" IsDriving="1" IsInVirtualSpace="0" IsActive="1" />
        <Constrain Name="" Type="1" Value="0" First="7" FirstPos="2" Second="8" SecondPos="1" Third="-2000" ThirdPos="0" LabelDistance="10" LabelPosition="0" IsDriving="1" IsInVirtualSpace="0" IsActive="1" />
        <Constrain Name="" Type="1" Value="0" First="8" FirstPos="2" Second="5" SecondPos="1" Third="-2000" ThirdPos="0" LabelDistance="10" LabelPosition="0" IsDriving="1" IsInVirtualSpace="0" IsActive="1" />
        <Constrain Name="" Type="2" Value="0" First="5" FirstPos="0" Second="-2000" SecondPos="0" Third="-2000" ThirdPos="0" LabelDistance="10" LabelPosition="0" IsDriving="1" IsInVirtualSpace="0" IsActive="1" />
        <Constrain Name="" Type="2" Value="0" First="7" FirstPos="0" Second="-2000" SecondPos="0" Third="-2000" ThirdPos="0" LabelDistance="10" LabelPosition="0" IsDriving="1" IsInVirtualSpace="0" IsActive="1" />
        <Constrain Name="" Type="3" Value="0" First="6" FirstPos="0" Second="-2000" SecondPos="0" Third="-2000" ThirdPos="0" LabelDistance="10" LabelPosition="0" IsDriving="1" IsInVirtualSpace="0" IsActive="1" />
        <Constrain Name="" Type="3" Value="0" First="8" FirstPos="0" Second="-2000" SecondPos="0" Third="-2000" ThirdPos="0" LabelDistance="10" LabelPosition="0" IsDriving="1" IsInVirtualSpace="0" IsActive="1" />
        <Constrain Name="" Type="1" Value="0" First="5" FirstPos="1" Second="-3" SecondPos="1" Third="-2000" ThirdPos="0" LabelDistance="10" LabelPosition="0" IsDriving="1" IsInVirtualSpace="0" IsActive="1" />
        <Constrain Name="" Type="13" Value="0" First="6" FirstPos="2" Second="-4" SecondPos="0" Third="-2000" ThirdPos="0" LabelDistance="10" LabelPosition="0" IsDriving="1" IsInVirtualSpace="0" IsActive="1" />
        <Constrain Name="" Type="8" Value="8.33" First="3" FirstPos="2" Second="6" SecondPos="2" Third="-2000" ThirdPos="0" LabelDistance="1.188482165336609" LabelPosition="0" IsDriving="1" IsInVirtualSpace="0" IsActive="1" />
      </ConstraintList>
    </Property>
    <Property name="Exports" type="App::PropertyLinkListHidden" status="67108864">
      <LinkList count="0">
      </LinkList>
    </Property>
    <Property name="ExpressionEngine" type="App::PropertyExpressionEngine" status="67108864">
      <ExpressionEngine count="0"></ExpressionEngine>
    </Property>
    <Property name="ExternalBSplineMaxDegree" type="App::PropertyInteger">
      <Integer value="5"/>
    </Property>
    <Property name="ExternalBSplineTolerance" type="App::PropertyPrecision">
      <Float value="0.0001"/>
    </Property>
    <Property name="ExternalGeo" type="Part::PropertyGeometryList" status="67108864">
      <GeometryList count="4">
        <Geometry type="Part::GeomLineSegment" id="-1" migrated="1">
          <GeoExtensions count="2">
            <GeoExtension type="Sketcher::SketchGeometryExtension" id="-1" internalGeometryType="0" geometryModeFlags="00000000000000000000000000000010"/>
            <GeoExtension type="Sketcher::ExternalGeometryExtension" Ref="" Flags="0"/>
          </GeoExtensions>
          <LineSegment StartX="0" StartY="0" StartZ="0" EndX="1" EndY="0" EndZ="0"/>
          <Construction value="1"/>
        </Geometry>
        <Geometry type="Part::GeomLineSegment" id="-2" migrated="1">
          <GeoExtensions count="2">
            <GeoExtension type="Sketcher::SketchGeometryExtension" id="-2" internalGeometryType="0" geometryModeFlags="00000000000000000000000000000010"/>
            <GeoExtension type="Sketcher::ExternalGeometryExtension" Ref="" Flags="0"/>
          </GeoExtensions>
          <LineSegment StartX="0" StartY="0" StartZ="0" EndX="0" EndY="1" EndZ="0"/>
          <Construction value="1"/>
        </Geometry>
        <Geometry type="Part::GeomLineSegment" id="1" ref="Pad079.;#1a52e;:H1641,E" migrated="1">
          <GeoExtensions count="2">
            <GeoExtension type="Sketcher::SketchGeometryExtension" id="1" internalGeometryType="0" geometryModeFlags="00000000000000000000000000000010"/>
            <GeoExtension type="Sketcher::ExternalGeometryExtension" Ref="Pad079.;#1a52e;:H1641,E" Flags="0"/>
          </GeoExtensions>
          <LineSegment StartX="24.5" StartY="0" StartZ="0" EndX="24.5" EndY="-16.16" EndZ="0"/>
          <Construction value="1"/>
        </Geometry>
        <Geometry type="Part::GeomLineSegment" id="6" ref="Pad079.;#1a4e4;:H-163b,E" migrated="1">
          <GeoExtensions count="2">
            <GeoExtension type="Sketcher::SketchGeometryExtension" id="6" internalGeometryType="0" geometryModeFlags="00000000000000000000000000000010"/>
            <GeoExtension type="Sketcher::ExternalGeometryExtension" Ref="Pad079.;#1a4e4;:H-163b,E" Flags="0"/>
          </GeoExtensions>
          <LineSegment StartX="28.5" StartY="6.9e-15" StartZ="0" EndX="28.5" EndY="-16.15999999999999" EndZ="0"/>
          <Construction value="1"/>
        </Geometry>
      </GeometryList>
    </Property>
    <Property name="ExternalGeometry" type="App::PropertyLinkSubList" status="16777216">
      <LinkSubList count="2">
        <Link obj="Pad079" sub="Edge6" shadow=";#1a52e;:H1641,E.Edge6"/>
        <Link obj="Pad079" sub="Edge106" shadow=";#1a4e4;:H-163b,E.Edge106"/>
      </LinkSubList>
    </Property>
    <Property name="FixShape" type="App::PropertyEnumeration">
      <Integer value="0"/>
    </Property>
    <Property name="FullyConstrained" type="App::PropertyBool" status="218103808">
      <Bool value="true"/>
    </Property>
    <Property name="Geometry" type="Part::PropertyGeometryList" status="8192">
      <GeometryList count="9">
        <Geometry type="Part::GeomLineSegment" id="7" migrated="1">
          <GeoExtensions count="1">
            <GeoExtension type="Sketcher::SketchGeometryExtension" id="7" internalGeometryType="0" geometryModeFlags="00000000000000000000000000000000"/>
          </GeoExtensions>
          <LineSegment StartX="28.5" StartY="-11.65999999999999" StartZ="0" EndX="24.5" EndY="-15.65999999999999" EndZ="0"/>
          <Construction value="0"/>
        </Geometry>
        <Geometry type="Part::GeomLineSegment" id="9" migrated="1">
          <GeoExtensions count="1">
            <GeoExtension type="Sketcher::SketchGeometryExtension" id="9" internalGeometryType="0" geometryModeFlags="00000000000000000000000000000000"/>
          </GeoExtensions>
          <LineSegment StartX="28.5" StartY="-15.65999999999999" StartZ="0" EndX="28.5" EndY="-11.65999999999999" EndZ="0"/>
          <Construction value="0"/>
        </Geometry>
        <Geometry type="Part::GeomLineSegment" id="11" migrated="1">
          <GeoExtensions count="1">
            <GeoExtension type="Sketcher::SketchGeometryExtension" id="11" internalGeometryType="0" geometryModeFlags="00000000000000000000000000000000"/>
          </GeoExtensions>
          <LineSegment StartX="24.5" StartY="-15.65999999999999" StartZ="0" EndX="24.5" EndY="-16.16" EndZ="0"/>
          <Construction value="0"/>
        </Geometry>
        <Geometry type="Part::GeomLineSegment" id="12" migrated="1">
          <GeoExtensions count="1">
            <GeoExtension type="Sketcher::SketchGeometryExtension" id="12" internalGeometryType="0" geometryModeFlags="00000000000000000000000000000000"/>
          </GeoExtensions>
          <LineSegment StartX="24.5" StartY="-16.16" StartZ="0" EndX="28.5" EndY="-16.15999999999999" EndZ="0"/>
          <Construction value="0"/>
        </Geometry>
        <Geometry type="Part::GeomLineSegment" id="8" migrated="1">
          <GeoExtensions count="1">
            <GeoExtension type="Sketcher::SketchGeometryExtension" id="8" internalGeometryType="0" geometryModeFlags="00000000000000000000000000000000"/>
          </GeoExtensions>
          <LineSegment StartX="28.5" StartY="-16.15999999999999" StartZ="0" EndX="28.5" EndY="-15.65999999999999" EndZ="0"/>
          <Construction value="0"/>
        </Geometry>
        <Geometry type="Part::GeomLineSegment" id="13" migrated="1">
          <GeoExtensions count="1">
            <GeoExtension type="Sketcher::SketchGeometryExtension" id="13" internalGeometryType="0" geometryModeFlags="00000000000000000000000000000000"/>
          </GeoExtensions>
          <LineSegment StartX="24.5" StartY="0" StartZ="0" EndX="28.5" EndY="0" EndZ="0"/>
          <Construction value="0"/>
        </Geometry>
        <Geometry type="Part::GeomLineSegment" id="14" migrated="1">
          <GeoExtensions count="1">
            <GeoExtension type="Sketcher::SketchGeometryExtension" id="14" internalGeometryType="0" geometryModeFlags="00000000000000000000000000000000"/>
          </GeoExtensions>
          <LineSegment StartX="28.5" StartY="0" StartZ="0" EndX="28.5" EndY="-7.829999999999993" EndZ="0"/>
          <Construction value="0"/>
        </Geometry>
        <Geometry type="Part::GeomLineSegment" id="15" migrated="1">
          <GeoExtensions count="1">
            <GeoExtension type="Sketcher::SketchGeometryExtension" id="15" internalGeometryType="0" geometryModeFlags="00000000000000000000000000000000"/>
          </GeoExtensions>
          <LineSegment StartX="28.5" StartY="-7.829999999999993" StartZ="0" EndX="24.5" EndY="-7.829999999999993" EndZ="0"/>
          <Construction value="0"/>
        </Geometry>
        <Geometry type="Part::GeomLineSegment" id="16" migrated="1">
          <GeoExtensions count="1">
            <GeoExtension type="Sketcher::SketchGeometryExtension" id="16" internalGeometryType="0" geometryModeFlags="00000000000000000000000000000000"/>
          </GeoExtensions>
          <LineSegment StartX="24.5" StartY="-7.829999999999993" StartZ="0" EndX="24.5" EndY="0" EndZ="0"/>
          <Construction value="0"/>
        </Geometry>
      </GeometryList>
    </Property>
    <Property name="InternalShape" type="Part::PropertyPartShape">
      <Part ElementMap="0.15.70200.4" brep="1">
<![CDATA[

CASCADE Topology V1, (c) Matra-Datavision
Locations 0
Curve2ds 0
Curves 0
Polygon3D 0
PolygonOnTriangulations 0
Surfaces 0
Triangulations 0

TShapes 0

*]]>
      </Part>
      <ElementMap/>
    </Property>
    <Property name="InternalTolerance" type="App::PropertyPrecision">
      <Float value="1e-06"/>
    </Property>
    <Property name="InvalidShape" type="App::PropertyBool" status="67108864">
      <Bool value="false"/>
    </Property>
    <Property name="Label" type="App::PropertyString" status="134217728">
      <String value="Sketch191"/>
    </Property>
    <Property name="Label2" type="App::PropertyString" status="128">
      <String value=""/>
    </Property>
    <Property name="MakeInternals" type="App::PropertyBool">
      <Bool value="false"/>
    </Property>
    <Property name="MapMode" type="App::PropertyEnumeration">
      <Integer value="5"/>
    </Property>
    <Property name="MapPathParameter" type="App::PropertyFloat" status="8">
      <Float value="0"/>
    </Property>
    <Property name="MapReversed" type="App::PropertyBool">
      <Bool value="false"/>
    </Property>
    <Property name="Placement" type="App::PropertyPlacement" status="8388612">
      <PropertyPlacement Px="0" Py="-24.5" Pz="0" Q0="0.7071067811865475" Q1="0" Q2="0" Q3="0.7071067811865476" A="1.570796326794897" Ox="1" Oy="0" Oz="0"/>
    </Property>
    <Property name="Shape" type="Part::PropertyPartShape">
      <Part HasherIndex="0" ElementMap="1.15.70200.4" brep="1">
<![CDATA[

CASCADE Topology V1, (c) Matra-Datavision
Locations 1
1
              1               0               0               0 
              0 2.22044604925031e-16              -1           -24.5 
              0               1 2.22044604925031e-16               0 
Curve2ds 0
Curves 9
1 28.499999999999996 -11.659999999999995 0 -0.70710678118654735 -0.70710678118654768 0 
1 24.5 -15.659999999999993 0 0 -1 0 
1 24.5 -16.16 0 1 1.7763568394002505e-15 0 
1 28.5 -16.159999999999993 0 -7.1054273576010019e-15 1 0 
1 28.499999999999996 -15.659999999999993 0 0 1 0 
1 24.5 0 0 1 0 0 
1 28.499999999999996 0 0 0 -1 0 
1 28.499999999999996 -7.829999999999993 0 -1 0 0 
1 24.5 -7.829999999999993 0 0 1 0 
Polygon3D 0
PolygonOnTriangulations 0
Surfaces 0
Triangulations 0

TShapes 21
Ve
1e-07
28.5 -11.66 0
0 0

0101101
*
Ve
1e-07
24.5 -15.66 0
0 0

0101101
*
Ed
 1e-07 1 1 0
1  1 0 0 5.65685424949238
0

0101000
+21 0 -20 0 *
Ve
1e-07
24.5 -16.16 0
0 0

0101101
*
Ed
 1e-07 1 1 0
1  2 0 0 0.500000000000007
0

0101000
+20 0 -18 0 *
Ve
1e-07
28.5 -16.16 0
0 0

0101101
*
Ed
 1e-07 1 1 0
1  3 0 0 4
0

0101000
+18 0 -16 0 *
Ve
1e-07
28.5 -15.66 0
0 0

0101101
*
Ed
 1e-07 1 1 0
1  4 0 0 0.5
0

0101000
+16 0 -14 0 *
Ed
 1e-07 1 1 0
1  5 0 0 4
0

0101000
+14 0 -21 0 *
Wi

0101100
+19 0 +17 0 +15 0 +13 0 +12 0 *
Ve
1e-07
24.5 0 0
0 0

0101101
*
Ve
1e-07
28.5 0 0
0 0

0101101
*
Ed
 1e-07 1 1 0
1  6 0 0 4
0

0101000
+10 0 -9 0 *
Ve
1e-07
28.5 -7.82999999999999 0
0 0

0101101
*
Ed
 1e-07 1 1 0
1  7 0 0 7.82999999999999
0

0101000
+9 0 -7 0 *
Ve
1e-07
24.5 -7.82999999999999 0
0 0

0101101
*
Ed
 1e-07 1 1 0
1  8 0 0 4
0

0101000
+7 0 -5 0 *
Ed
 1e-07 1 1 0
1  9 0 0 7.82999999999999
0

0101000
+5 0 -10 0 *
Wi

0101100
+8 0 +6 0 +4 0 +3 0 *
Co

0100000
+11 0 +2 0 *

+1 1 ]]>
      </Part>
      <ElementMap new="1" count="1"><Element key="Dummy" value="Dummy"/></ElementMap>
      <ElementMap2 count="18">
<![CDATA[
679 PostfixCount 3
Edge
Vertex
;SKT

MapCount 2

ElementMap 1 680 2

Edge

ChildCount 0

NameCount 6
0
;g7.3 0
;g11.3 0
;g12.3 0
;g8.3 0
;g9.3 0

Vertex

ChildCount 0

NameCount 6
0
;g7v1.3 ;g9v2.3 0
;g7v2.3 ;g11v1.3 0
;g11v2.3 ;g12v1.3 0
;g12v2.3 ;g8v1.3 0
;g9v1.3 ;g8v2.3 0

EndMap

ElementMap 2 679 2

Edge

ChildCount 1
1 0 5 0 1 ;:H,E 0

NameCount 10
0
0
0
0
0
0
;g13.3 0
;g14.3 0
;g15.3 0
;g16.3 0

Vertex

ChildCount 1
1 0 5 0 1 ;:H,V 0

NameCount 10
0
0
0
0
0
0
;g13v1.3 0
;g13v2.3 0
;g14v2.3 0
;g15v2.3 0

EndMap
]]>
      </ElementMap2>
    </Property>
    <Property name="Support" type="App::PropertyLinkSubList" status="67108864">
      <LinkSubList count="1">
        <Link obj="Pad079" sub="Face1" shadow=";#1a594;:H1641,F.Face1"/>
      </LinkSubList>
    </Property>
    <Property name="TreeRank" type="App::PropertyInteger" status="2184">
      <Integer value="24"/>
    </Property>
    <Property name="ValidateShape" type="App::PropertyBool">
      <Bool value="true"/>
    </Property>
    <Property name="Visibility" type="App::PropertyBool" status="648">
      <Bool value="false"/>
    </Property>
  </Properties>
</Object>
</Document>
